multiCompare.py
multiCompare-0.0.3.dist-info/METADATA
multiCompare-0.0.3.dist-info/WHEEL
multiCompare-0.0.3.dist-info/entry_points.txt
multiCompare-0.0.3.dist-info/top_level.txt
multiCompare-0.0.3.dist-info/RECORD
