Metadata-Version: 2.1
Name: multiCompare
Version: 0.0.3
Summary: how to cert multi compare
Home-page: https://github.com/ryoryo34/multipleCompare
Author: ryouryou34
Author-email: ryouryou3434@gmail.com
Classifier: Programming Language :: Python :: 3
Classifier: License :: OSI Approved :: MIT License
Classifier: Operating System :: OS Independent
Requires-Python: >=3.7
